ready2order_api/__init__.py
ready2order_api/api.py
ready2order_api/bill.py
ready2order_api/company.py
ready2order_api/get_acct_token.py
ready2order_api/product.py
tests/__init__.py
ready2order_api_wrapper-0.1.10.dist-info/LICENSE
ready2order_api_wrapper-0.1.10.dist-info/METADATA
ready2order_api_wrapper-0.1.10.dist-info/WHEEL
ready2order_api_wrapper-0.1.10.dist-info/top_level.txt
ready2order_api_wrapper-0.1.10.dist-info/RECORD
